{
	"backtraceGraph" : 
	{
		"commands" : 
		[
			"install"
		],
		"files" : 
		[
			"CMakeLists.txt"
		],
		"nodes" : 
		[
			{
				"file" : 0
			},
			{
				"command" : 0,
				"file" : 0,
				"line" : 81,
				"parent" : 0
			},
			{
				"command" : 0,
				"file" : 0,
				"line" : 92,
				"parent" : 0
			},
			{
				"command" : 0,
				"file" : 0,
				"line" : 97,
				"parent" : 0
			},
			{
				"command" : 0,
				"file" : 0,
				"line" : 100,
				"parent" : 0
			},
			{
				"command" : 0,
				"file" : 0,
				"line" : 104,
				"parent" : 0
			}
		]
	},
	"installers" : 
	[
		{
			"backtrace" : 1,
			"component" : "Unspecified",
			"destination" : "bin",
			"paths" : 
			[
				"comet"
			],
			"targetId" : "comet-exe::@6890427a1f51a3e7e1df",
			"targetIndex" : 29,
			"type" : "target"
		},
		{
			"backtrace" : 2,
			"component" : "Unspecified",
			"destination" : "lib",
			"paths" : 
			[
				"libcomet.so"
			],
			"targetId" : "comet::@6890427a1f51a3e7e1df",
			"targetIndex" : 28,
			"type" : "target"
		},
		{
			"backtrace" : 3,
			"component" : "Unspecified",
			"destination" : "include/comet",
			"paths" : 
			[
				{
					"from" : "src",
					"to" : "."
				}
			],
			"type" : "directory"
		},
		{
			"backtrace" : 4,
			"component" : "Unspecified",
			"destination" : "share/comet",
			"exportName" : "comet-config",
			"exportTargets" : 
			[
				{
					"id" : "comet::@6890427a1f51a3e7e1df",
					"index" : 28
				}
			],
			"paths" : 
			[
				"CMakeFiles/Export/a553b9c385137e5b5649a36ac0e43547/comet-config.cmake"
			],
			"type" : "export"
		},
		{
			"backtrace" : 5,
			"component" : "Unspecified",
			"destination" : "share/comet",
			"paths" : 
			[
				"build/comet-config-version.cmake"
			],
			"type" : "file"
		}
	],
	"paths" : 
	{
		"build" : ".",
		"source" : "."
	}
}
